scdev_pd_column/__init__.py
scdev_pd_column/example.py
voidray_pkg_scdev_pd_columns-0.0.1.dist-info/LICENSE.txt
voidray_pkg_scdev_pd_columns-0.0.1.dist-info/METADATA
voidray_pkg_scdev_pd_columns-0.0.1.dist-info/WHEEL
voidray_pkg_scdev_pd_columns-0.0.1.dist-info/top_level.txt
voidray_pkg_scdev_pd_columns-0.0.1.dist-info/RECORD
