Metadata-Version: 2.1
Name: voidray-pkg-scdev-pd-columns
Version: 0.0.1
Summary: schooldevops sample lib
Home-page: https://github.com/schooldevops/python-tutorials
Author: Schooldevops
Author-email: schooldevops@gmail.com
Project-URL: Bug Tracker, https://github.com/schooldevops/python-tutorials/issues
Classifier: Programming Language :: Python :: 3
Classifier: License :: OSI Approved :: MIT License
Classifier: Operating System :: OS Independent
Requires-Python: >=3.6
License-File: LICENSE.txt
